Metadata-Version: 1.0
Name: mau-test-distributions
Version: 0.1
Summary: Gaussian distributions
Home-page: UNKNOWN
Author: Mauricio Maroto
Author-email: UNKNOWN
License: UNKNOWN
Platform: UNKNOWN
